improvedgan/__init__.py
improvedgan_pytorch-0.1.0.dist-info/METADATA
improvedgan_pytorch-0.1.0.dist-info/WHEEL
improvedgan_pytorch-0.1.0.dist-info/RECORD
